MANIFEST.in
README.md
requirements.txt
setup.py
conf/__init__.py
conf/conf_logs.py
src/__init__.py
src/__main__.py
src/boto_connections.py
src/clean_cloudformation.py
src/clean_ec2_instances.py
src/clean_launchconfiguration.py
src/clean_snapshots.py
src/cleaner_ecr.py
src/cli.py
src/get_sts.py
src/wall_e.py
tests/__init__.py
tests/test_clean_launchconfiguration.py
tests/test_ecr_repositories.py
tests/test_walle_configuration.py
wall_e.egg-info/PKG-INFO
wall_e.egg-info/SOURCES.txt
wall_e.egg-info/dependency_links.txt
wall_e.egg-info/entry_points.txt
wall_e.egg-info/requires.txt
wall_e.egg-info/top_level.txt