Metadata-Version: 1.0
Name: wall-e
Version: 1.0.1
Summary: Clean your account AWS
Home-page: https://github.com/ismFerDev/Wall-e
Author: Ismael Fernandez
Author-email: fernandez.molina.ismael@gmail.com
License: GPLv2
Platform: UNKNOWN
